pandasdb/__init__.py
pandasdb/airflow.py
pandasdb/transform.py
pandasdb/communication/__init__.py
pandasdb/communication/errors/__init__.py
pandasdb/communication/errors/base.py
pandasdb/communication/errors/io.py
pandasdb/communication/errors/transform.py
pandasdb/communication/errors/validation.py
pandasdb/libraries/__init__.py
pandasdb/libraries/configuration/__init__.py
pandasdb/libraries/configuration/src/__init__.py
pandasdb/libraries/configuration/src/base.py
pandasdb/libraries/configuration/src/database_config.py
pandasdb/libraries/configuration/src/oauth_config.py
pandasdb/libraries/configuration/src/tunnelled_config.py
pandasdb/libraries/connections/__init__.py
pandasdb/libraries/connections/alchemy.py
pandasdb/libraries/connections/qsuite.py
pandasdb/libraries/easy_config/__init__.py
pandasdb/libraries/easy_config/src/__init__.py
pandasdb/libraries/easy_config/src/example.py
pandasdb/libraries/easy_config/src/configurable/__init__.py
pandasdb/libraries/easy_config/src/configurable/conditional.py
pandasdb/libraries/easy_config/src/configurable/group.py
pandasdb/libraries/easy_config/src/configurable/parameter.py
pandasdb/libraries/easy_config/src/configurable/submit.py
pandasdb/libraries/easy_config/src/configurable/validator.py
pandasdb/libraries/graph/__init__.py
pandasdb/libraries/graph/src/__init__.py
pandasdb/libraries/graph/src/plot.py
pandasdb/libraries/graph/src/table_graph.py
pandasdb/libraries/overrides/__init__.py
pandasdb/libraries/overrides/src/__init__.py
pandasdb/libraries/overrides/src/lazy.py
pandasdb/libraries/overrides/src/representable.py
pandasdb/libraries/pandas/__init__.py
pandasdb/libraries/pandas/src/__init__.py
pandasdb/libraries/pandas/src/types.py
pandasdb/libraries/parallel/__init__.py
pandasdb/libraries/parallel/src/__init__.py
pandasdb/libraries/parallel/src/async_pool.py
pandasdb/libraries/utils/__init__.py
pandasdb/libraries/utils/src/__init__.py
pandasdb/services/__init__.py
pandasdb/services/airflow/__init__.py
pandasdb-0.1.27.dist-info/METADATA
pandasdb-0.1.27.dist-info/WHEEL
pandasdb-0.1.27.dist-info/top_level.txt
pandasdb-0.1.27.dist-info/RECORD
